MANIFEST.in
README.txt
distribute_setup.py
setup.py
doc/long_description.txt
doc/HttpClientUml/128002
doc/HttpClientUml/128002.diagram
doc/HttpClientUml/128130
doc/HttpClientUml/2.session
doc/HttpClientUml/HttpClientUml.prj
doc/HttpClientUml/cpp_includes
doc/HttpClientUml/generation_settings
doc/HttpClientUml/idl_includes
doc/HttpClientUml/java_imports
doc/HttpClientUml/python_imports
doc/HttpClientUml/stereotypes
doc/HttpClientUml/tools
src/httpclient/__init__.py
src/httpclient/httpclient.py
src/httpclient/httpcore.py
src/httpclient.egg-info/PKG-INFO
src/httpclient.egg-info/SOURCES.txt
src/httpclient.egg-info/dependency_links.txt
src/httpclient.egg-info/top_level.txt
src/httpclient_test/__init__.py
src/httpclient_test/functionaltest/__init__.py
src/httpclient_test/functionaltest/httpclient_test.py
src/httpclient_test/functionaltest/server.py
src/httpclient_test/unittest/__init__.py
src/httpclient_test/unittest/httpclient_test.py
src/httpclient_test/unittest/httpcore_test.py