Metadata-Version: 1.0
Name: httpclient
Version: 0.0.2
Summary: A headless HTTP browser.
Home-page: https://github.com/guillaume-humbert/httpclient
Author: Guillaume Humbert
Author-email: guillaume.humbert.jp@gmail.com
License: GNU General Public License (GPL) v3
Download-URL: https://github.com/guillaume-humbert/httpclient
Keywords: http headless browser crawler html
Platform: Unix
Platform: Windows
Classifier: Development Status :: 3 - Alpha
Classifier: Intended Audience :: Developers
Classifier: License :: OSI Approved :: GNU General Public License (GPL)
Classifier: Natural Language :: English
Classifier: Operating System :: OS Independent
Classifier: Programming Language :: Python :: 3.2
Classifier: Topic :: Internet :: WWW/HTTP
Classifier: Topic :: Internet :: WWW/HTTP :: Browsers
